[
  {
    "model": "dsd.category",
    "pk": "qc4570d5a32",
    "fields": {
      "name": "sarampo tempo intervalo",
      "category_options": [
        "eb9f34026a3",
        "cff3b4f3f84",
        "u0185f2b3eb",
        "t15u59j77e2"
      ]
    }
  },
  {
    "model": "dsd.category",
    "pk": "h40afc251b2",
    "fields": {
      "name": "malaria tempo intervalo",
      "category_options": [
        "Lab5e311f4d",
        "p9532d3b911"
      ]
    }
  },
  {
    "model": "dsd.category",
    "pk": "tec63d04fce",
    "fields": {
      "name": "malaria clinica tempo intervalo",
      "category_options": [
        "Lab5e311f4d",
        "p9532d3b911"
      ]
    }
  },
  {
    "model": "dsd.category",
    "pk": "d6850b46c58",
    "fields": {
      "name": "diarreia tempo intervalo",
      "category_options": [
        "Lab5e311f4d",
        "c77d65db82c",
        "ebbe4c65238"
      ]
    }
  },
  {
    "model": "dsd.category",
    "pk": "f397a34ae8e",
    "fields": {
      "name": "meningite tempo intervalo",
      "category_options": [
        "Lab5e311f4d",
        "p9532d3b911"
      ]
    }
  },
  {
    "model": "dsd.category",
    "pk": "y1b2d794df8",
    "fields": {
      "name": "indice de doenca",
      "category_options": [
        "rc8d41da389",
        "e8a197f3d83"
      ]
    }
  }
]